add_subagent/__init__.py
add_subagent-0.0.1.dist-info/METADATA
add_subagent-0.0.1.dist-info/WHEEL
add_subagent-0.0.1.dist-info/RECORD
