Metadata-Version: 2.4
Name: add-subagent
Version: 0.0.1
Summary: CLI tool for adding Claude Code subagents from GitHub. Coming soon.
Project-URL: Repository, https://github.com/kasperjunge/agent-resources
License-Expression: MIT
Keywords: agent,ai,claude,claude-code,subagent
Requires-Python: >=3.10
